makar72/3.txt
makar72/4.txt
makar72/5.txt
makar72/__init__.py
makar72-0.1.0.dist-info/METADATA
makar72-0.1.0.dist-info/WHEEL
makar72-0.1.0.dist-info/top_level.txt
makar72-0.1.0.dist-info/RECORD
