Metadata-Version: 2.4
Name: makar72
Version: 0.1.0
Summary: Че надо
Author: Ваше Имя
Classifier: Programming Language :: Python :: 3
Classifier: License :: OSI Approved :: MIT License
Classifier: Operating System :: OS Independent
Requires-Python: >=3.7
Dynamic: author
Dynamic: classifier
Dynamic: requires-python
Dynamic: summary
